murdocktools/compare.py
murdocktools/convert.py
murdocktools/options.py
murdocktools/config.py
murdocktools/split.py
murdocktools/__init__.py
murdocktools/report.py
murdocktools/tables.py
murdock/molstruct.py
murdock/pymol.py
murdock/config.py
murdock/math.py
murdock/misc.py
murdock/logger.py
murdock/__init__.py
murdock/tree.py
murdock/plot.py
murdock/results.py
murdock/__main__.py
murdock/transforms.py
murdock/murdock.py
murdock/scoring/scoring.py
murdock/scoring/__init__.py
murdock/scoring/rmsd.py
murdock/scoring/custom.py
murdock/scoring/pool.py
murdock/runner/screening.py
murdock/runner/__init__.py
murdock/runner/docking.py
murdock/runner/training.py
murdock/runner/runner.py
murdock/moldata/moldata.py
murdock/moldata/__init__.py
murdock/moldata/pdb.py
murdock/moldata/mol2.py
murdock/test/test_misc.py
murdock/test/test_screening.py
murdock/test/test_report.py
murdock/test/test_molstruct.py
murdock/test/__init__.py
murdock/test/test_scoring.py
murdock/test/test_results.py
murdock/test/test_transforms.py
murdock/test/test_docking.py
murdock/test/data/ligand2.mol2
murdock/test/data/ligand1.mol2
murdock/test/data/receptor2.mol2
murdock/test/data/receptor3.mol2
murdock/test/data/receptor1.mol2
murdock/test/data/ligand3.mol2
murdock/custom/pmemd.py
murdock/custom/__init__.py
murdock/custom/frcmod.py
murdock/custom/gags.py
murdock/custom/flexx.py
murdock/custom/ehits.py
murdock/data/config_presets/rigid-preset.json
murdock/data/config_presets/default-preset.json
murdock/data/config_presets/default-info.txt
murdock/data/config_presets/bioinfp_gag-info.txt
murdock/data/config_presets/bioinfp_gag_cg-info.txt
murdock/data/config_presets/flexible-preset.json
murdock/data/config_presets/bioinfp_gag_cg-preset.json
murdock/data/config_presets/rigid-info.txt
murdock/data/config_presets/bioinfp_gag-preset.json
murdock/data/config_presets/flexible-info.txt
murdock/data/html_themes/bootstrap/layout.html
murdock-0.10.12.dist-info/METADATA
murdock-0.10.12.dist-info/DESCRIPTION.rst
murdock-0.10.12.dist-info/WHEEL
murdock-0.10.12.dist-info/top_level.txt
murdock-0.10.12.dist-info/entry_points.txt
murdock-0.10.12.dist-info/metadata.json
murdock-0.10.12.dist-info/RECORD
