Metadata-Version: 2.0
Name: murdock
Version: 0.10.12
Summary: A molecular docking framework.
Home-page: http://bitbucket.org/mlichtner/murdock
Author: Malte Lichtner
Author-email: murdock@mlichtner.de
License: Apache 2.0
Keywords: molecular docking development framework
Platform: UNKNOWN
Classifier: Development Status :: 3 - Alpha
Classifier: Intended Audience :: Science/Research
Classifier: Topic :: Scientific/Engineering :: Bio-Informatics
Classifier: License :: OSI Approved :: Apache Software License
Classifier: Programming Language :: Python :: 2.7
Classifier: Programming Language :: Python :: 3.2
Classifier: Programming Language :: Python :: 3.3
Classifier: Programming Language :: Python :: 3.4
Classifier: Programming Language :: Python :: 3.6
Requires-Dist: future (>=0.15)
Requires-Dist: numpy (>=1.6)
Requires-Dist: scipy (>=0.11)
Provides-Extra: html
Requires-Dist: sphinx (>=1.1); extra == 'html'
Provides-Extra: plots
Requires-Dist: matplotlib (>=1.2); extra == 'plots'
